distgen/__init__.py
distgen/__main__.py
distgen/cli_parser.py
distgen/commands.py
distgen/config.py
distgen/distro_version.py
distgen/err.py
distgen/generator.py
distgen/multispec.py
distgen/pathmanager.py
distgen/project.py
distgen/distconf/centos-6-x86_64.yaml
distgen/distconf/centos-7-x86_64.yaml
distgen/distconf/centos-8-x86_64.yaml
distgen/distconf/centos-stream-10-x86_64.yaml
distgen/distconf/centos-stream-8-x86_64.yaml
distgen/distconf/centos-stream-9-x86_64.yaml
distgen/distconf/fedora-20-i686.yaml
distgen/distconf/fedora-20-x86_64.yaml
distgen/distconf/fedora-21-i686.yaml
distgen/distconf/fedora-21-x86_64.yaml
distgen/distconf/fedora-22-i686.yaml
distgen/distconf/fedora-22-x86_64.yaml
distgen/distconf/fedora-23-i686.yaml
distgen/distconf/fedora-23-x86_64.yaml
distgen/distconf/fedora-24-i686.yaml
distgen/distconf/fedora-24-x86_64.yaml
distgen/distconf/fedora-25-i686.yaml
distgen/distconf/fedora-25-x86_64.yaml
distgen/distconf/fedora-26-i686.yaml
distgen/distconf/fedora-26-x86_64.yaml
distgen/distconf/fedora-27-i686.yaml
distgen/distconf/fedora-27-x86_64.yaml
distgen/distconf/fedora-28-i686.yaml
distgen/distconf/fedora-28-x86_64.yaml
distgen/distconf/fedora-29-i686.yaml
distgen/distconf/fedora-29-x86_64.yaml
distgen/distconf/fedora-30-i686.yaml
distgen/distconf/fedora-30-x86_64.yaml
distgen/distconf/fedora-31-i686.yaml
distgen/distconf/fedora-31-x86_64.yaml
distgen/distconf/fedora-32-i686.yaml
distgen/distconf/fedora-32-x86_64.yaml
distgen/distconf/fedora-33-i686.yaml
distgen/distconf/fedora-33-x86_64.yaml
distgen/distconf/fedora-34-i686.yaml
distgen/distconf/fedora-34-x86_64.yaml
distgen/distconf/fedora-35-i686.yaml
distgen/distconf/fedora-35-x86_64.yaml
distgen/distconf/fedora-36-i686.yaml
distgen/distconf/fedora-36-x86_64.yaml
distgen/distconf/fedora-37-i686.yaml
distgen/distconf/fedora-37-x86_64.yaml
distgen/distconf/fedora-38-i686.yaml
distgen/distconf/fedora-38-x86_64.yaml
distgen/distconf/fedora-39-i686.yaml
distgen/distconf/fedora-39-x86_64.yaml
distgen-2.2.dist-info/licenses/LICENSE
distgen-2.2.dist-info/METADATA
distgen-2.2.dist-info/WHEEL
distgen-2.2.dist-info/entry_points.txt
distgen-2.2.dist-info/top_level.txt
distgen-2.2.dist-info/RECORD
