Metadata-Version: 2.4
Name: distgen
Version: 2.2
Summary: Templating system/generator for distributions
Author: Red Hat Databases team
Maintainer-email: Ales Nezbeda <anezbeda@redhat.com>
License:                     GNU GENERAL PUBLIC LICENSE
Classifier: Development Status :: 5 - Production/Stable
Classifier: Programming Language :: Python :: 3
Classifier: License :: OSI Approved :: GNU General Public License v2 or later (GPLv2+)
Requires-Python: >=3.9
License-File: LICENSE
Requires-Dist: distro
Requires-Dist: jinja2
Requires-Dist: pyyaml
Requires-Dist: setuptools
Dynamic: license-file
